{"sections":{"main":{"type":"Page-template-new","settings":{"main_background_color":"#ffffff"}},"custom_liquid_7QERKb":{"type":"custom-liquid","settings":{"custom_liquid":"<div class=\"customization-tailoring\">\n    <div class=\"pagebuilder-column-group\">\n        <div class=\"pagebuilder-column\">\n            <h1>Customization &amp;\n                Tailoring<\/h1>\n            <div data-content-type=\"text\" data-appearance=\"default\" data-element=\"main\" bis_skin_checked=\"1\">\n                <h2>Blouse Stitching<\/h2>\n                <ul>\n                    <li>Blouse Stitching for choli style regular blouse Rs 2,100\/- USD 35<\/li>\n                    <li>Designer Blouse Rs 3,300 \/ USD 55<\/li>\n                <\/ul>\n                <h2>Pre-stitched saree<\/h2>\n                <ul>\n                    <li>INR 3,000 \/ 50 USD<\/li>\n                <\/ul>\n                <h2>Sleeve<\/h2>\n                <ul>\n                    <li>Plain net ¾ \/ half \/ full sleeves with no work: INR 600 \/ USD 10<\/li>\n                <\/ul>\n                <h2>Back coverin<\/h2>\n                <ul>\n                    <li>with net fabric INR 900 \/ USD 15<\/li>\n                    <li>with net fabric and lining INR 1,200 \/ USD 20<\/li>\n                <\/ul>\n                <h2>Dupatta<\/h2>\n                <ul>\n                    <li>Plain net dupatta with satin border INR 1,800 \/ USD 30<\/li>\n                    <li>Net dupatta with Small border and butti work: INR 6,000 \/ USD 100<\/li>\n                    <li>Bridal net dupatta with work INR 9,600 - 18,000 \/ USD 160 - 300<\/li>\n                    <li>Net with ruffle INR 4,200 \/ USD 70<\/li>\n                    <li>Net dupatta in abla work with cut dana border. INR 6,000 \/ USD 100<\/li>\n                <\/ul>\n                <h2>Tassel<\/h2>\n                <ul>\n                    <li>Regular Fabric or Golden Balls set - INR 600\/ USD 10&nbsp;<\/li>\n                    <li>Heavy Latkan RS 1800\/ USD 25.&nbsp;<\/li>\n                    <li>Designer embroidery Latkan 3,000\/ USD 50.&nbsp;<\/li>\n                    <li>Personalised latkan RS 4,200 \/ USD 70<\/li>\n                <\/ul>\n                <h2>MASK<\/h2>\n                <ul>\n                    <li>Embroidered Mask - Rs. 2100 \/ USD 35<\/li>\n                    <li>Plain fabric Mask - Free<\/li>\n                <\/ul>\n            <\/div>\n\n            \n                <img style=\"max-width: 100%;height: auto;\" src=\"https:\/\/cdn.shopify.com\/s\/files\/1\/0636\/0134\/4666\/files\/new-foot.jpg?v=1739161726\" alt=\"New Arrivals\" \/>\n        <\/div>\n    <\/div>\n<\/div>","color_scheme":"","padding_top":40,"padding_bottom":52}}},"order":["main","custom_liquid_7QERKb"]}